[
    {
      "lines": [
        {
          "text": "The Lord is",
          "boundingPolygon": [
            {
              "x": 550,
              "y": 100
            },
            {
              "x": 823,
              "y": 94
            },
            {
              "x": 825,
              "y": 159
            },
            {
              "x": 550,
              "y": 165
            }
          ],
          "words": [
            {
              "text": "The",
              "boundingPolygon": [
                {
                  "x": 556,
                  "y": 101
                },
                {
                  "x": 642,
                  "y": 98
                },
                {
                  "x": 642,
                  "y": 165
                },
                {
                  "x": 554,
                  "y": 165
                }
              ],
              "confidence": 0.975
            },
            {
              "text": "Lord",
              "boundingPolygon": [
                {
                  "x": 655,
                  "y": 97
                },
                {
                  "x": 767,
                  "y": 95
                },
                {
                  "x": 768,
                  "y": 161
                },
                {
                  "x": 655,
                  "y": 165
                }
              ],
              "confidence": 0.987
            },
            {
              "text": "is",
              "boundingPolygon": [
                {
                  "x": 780,
                  "y": 95
                },
                {
                  "x": 824,
                  "y": 95
                },
                {
                  "x": 825,
                  "y": 159
                },
                {
                  "x": 781,
                  "y": 161
                }
              ],
              "confidence": 0.994
            }
          ]
        },
        {
          "text": "my sheplerd:",
          "boundingPolygon": [
            {
              "x": 556,
              "y": 166
            },
            {
              "x": 856,
              "y": 157
            },
            {
              "x": 857,
              "y": 214
            },
            {
              "x": 556,
              "y": 226
            }
          ],
          "words": [
            {
              "text": "my",
              "boundingPolygon": [
                {
                  "x": 557,
                  "y": 168
                },
                {
                  "x": 634,
                  "y": 164
                },
                {
                  "x": 634,
                  "y": 224
                },
                {
                  "x": 557,
                  "y": 227
                }
              ],
              "confidence": 0.889
            },
            {
              "text": "sheplerd:",
              "boundingPolygon": [
                {
                  "x": 650,
                  "y": 163
                },
                {
                  "x": 854,
                  "y": 158
                },
                {
                  "x": 854,
                  "y": 216
                },
                {
                  "x": 650,
                  "y": 223
                }
              ],
              "confidence": 0.917
            }
          ]
        },
        {
          "text": "De meill",
          "boundingPolygon": [
            {
              "x": 542,
              "y": 267
            },
            {
              "x": 770,
              "y": 263
            },
            {
              "x": 772,
              "y": 324
            },
            {
              "x": 545,
              "y": 332
            }
          ],
          "words": [
            {
              "text": "De",
              "boundingPolygon": [
                {
                  "x": 547,
                  "y": 267
                },
                {
                  "x": 638,
                  "y": 269
                },
                {
                  "x": 640,
                  "y": 329
                },
                {
                  "x": 549,
                  "y": 333
                }
              ],
              "confidence": 0.648
            },
            {
              "text": "meill",
              "boundingPolygon": [
                {
                  "x": 650,
                  "y": 270
                },
                {
                  "x": 769,
                  "y": 264
                },
                {
                  "x": 770,
                  "y": 321
                },
                {
                  "x": 652,
                  "y": 329
                }
              ],
              "confidence": 0.662
            }
          ]
        },
        {
          "text": "my shaberd,",
          "boundingPolygon": [
            {
              "x": 545,
              "y": 325
            },
            {
              "x": 842,
              "y": 320
            },
            {
              "x": 843,
              "y": 387
            },
            {
              "x": 545,
              "y": 391
            }
          ],
          "words": [
            {
              "text": "my",
              "boundingPolygon": [
                {
                  "x": 545,
                  "y": 328
                },
                {
                  "x": 622,
                  "y": 325
                },
                {
                  "x": 622,
                  "y": 389
                },
                {
                  "x": 545,
                  "y": 391
                }
              ],
              "confidence": 0.989
            },
            {
              "text": "shaberd,",
              "boundingPolygon": [
                {
                  "x": 635,
                  "y": 325
                },
                {
                  "x": 841,
                  "y": 321
                },
                {
                  "x": 841,
                  "y": 389
                },
                {
                  "x": 635,
                  "y": 389
                }
              ],
              "confidence": 0.819
            }
          ]
        },
        {
          "text": "he makes me",
          "boundingPolygon": [
            {
              "x": 544,
              "y": 381
            },
            {
              "x": 843,
              "y": 385
            },
            {
              "x": 842,
              "y": 449
            },
            {
              "x": 544,
              "y": 447
            }
          ],
          "words": [
            {
              "text": "he",
              "boundingPolygon": [
                {
                  "x": 545,
                  "y": 382
                },
                {
                  "x": 594,
                  "y": 385
                },
                {
                  "x": 593,
                  "y": 449
                },
                {
                  "x": 544,
                  "y": 449
                }
              ],
              "confidence": 0.851
            },
            {
              "text": "makes",
              "boundingPolygon": [
                {
                  "x": 606,
                  "y": 385
                },
                {
                  "x": 757,
                  "y": 390
                },
                {
                  "x": 757,
                  "y": 449
                },
                {
                  "x": 605,
                  "y": 449
                }
              ],
              "confidence": 0.993
            },
            {
              "text": "me",
              "boundingPolygon": [
                {
                  "x": 770,
                  "y": 390
                },
                {
                  "x": 843,
                  "y": 389
                },
                {
                  "x": 843,
                  "y": 449
                },
                {
                  "x": 769,
                  "y": 449
                }
              ],
              "confidence": 0.989
            }
          ]
        },
        {
          "text": "liese down",
          "boundingPolygon": [
            {
              "x": 571,
              "y": 448
            },
            {
              "x": 825,
              "y": 450
            },
            {
              "x": 824,
              "y": 512
            },
            {
              "x": 571,
              "y": 510
            }
          ],
          "words": [
            {
              "text": "liese",
              "boundingPolygon": [
                {
                  "x": 574,
                  "y": 448
                },
                {
                  "x": 684,
                  "y": 450
                },
                {
                  "x": 683,
                  "y": 512
                },
                {
                  "x": 571,
                  "y": 511
                }
              ],
              "confidence": 0.992
            },
            {
              "text": "down",
              "boundingPolygon": [
                {
                  "x": 696,
                  "y": 451
                },
                {
                  "x": 818,
                  "y": 451
                },
                {
                  "x": 818,
                  "y": 513
                },
                {
                  "x": 695,
                  "y": 512
                }
              ],
              "confidence": 0.656
            }
          ]
        },
        {
          "text": "He creem apeestrer's,",
          "boundingPolygon": [
            {
              "x": 342,
              "y": 503
            },
            {
              "x": 840,
              "y": 515
            },
            {
              "x": 839,
              "y": 582
            },
            {
              "x": 341,
              "y": 575
            }
          ],
          "words": [
            {
              "text": "He",
              "boundingPolygon": [
                {
                  "x": 356,
                  "y": 504
                },
                {
                  "x": 419,
                  "y": 506
                },
                {
                  "x": 418,
                  "y": 578
                },
                {
                  "x": 355,
                  "y": 576
                }
              ],
              "confidence": 0.953
            },
            {
              "text": "creem",
              "boundingPolygon": [
                {
                  "x": 433,
                  "y": 507
                },
                {
                  "x": 562,
                  "y": 511
                },
                {
                  "x": 561,
                  "y": 581
                },
                {
                  "x": 432,
                  "y": 578
                }
              ],
              "confidence": 0.611
            },
            {
              "text": "apeestrer's,",
              "boundingPolygon": [
                {
                  "x": 585,
                  "y": 512
                },
                {
                  "x": 837,
                  "y": 520
                },
                {
                  "x": 837,
                  "y": 582
                },
                {
                  "x": 585,
                  "y": 582
                }
              ],
              "confidence": 0.573
            }
          ]
        },
        {
          "text": "In legno till pantuers,",
          "boundingPolygon": [
            {
              "x": 337,
              "y": 573
            },
            {
              "x": 847,
              "y": 588
            },
            {
              "x": 846,
              "y": 662
            },
            {
              "x": 336,
              "y": 653
            }
          ],
          "words": [
            {
              "text": "In",
              "boundingPolygon": [
                {
                  "x": 338,
                  "y": 574
                },
                {
                  "x": 393,
                  "y": 575
                },
                {
                  "x": 392,
                  "y": 655
                },
                {
                  "x": 337,
                  "y": 655
                }
              ],
              "confidence": 0.266
            },
            {
              "text": "legno",
              "boundingPolygon": [
                {
                  "x": 408,
                  "y": 576
                },
                {
                  "x": 532,
                  "y": 580
                },
                {
                  "x": 532,
                  "y": 657
                },
                {
                  "x": 407,
                  "y": 656
                }
              ],
              "confidence": 0.652
            },
            {
              "text": "till",
              "boundingPolygon": [
                {
                  "x": 547,
                  "y": 580
                },
                {
                  "x": 611,
                  "y": 583
                },
                {
                  "x": 612,
                  "y": 658
                },
                {
                  "x": 547,
                  "y": 657
                }
              ],
              "confidence": 0.984
            },
            {
              "text": "pantuers,",
              "boundingPolygon": [
                {
                  "x": 626,
                  "y": 583
                },
                {
                  "x": 845,
                  "y": 593
                },
                {
                  "x": 846,
                  "y": 662
                },
                {
                  "x": 627,
                  "y": 659
                }
              ],
              "confidence": 0.959
            }
          ]
        },
        {
          "text": "He leads me me",
          "boundingPolygon": [
            {
              "x": 344,
              "y": 656
            },
            {
              "x": 771,
              "y": 657
            },
            {
              "x": 771,
              "y": 733
            },
            {
              "x": 343,
              "y": 732
            }
          ],
          "words": [
            {
              "text": "He",
              "boundingPolygon": [
                {
                  "x": 356,
                  "y": 657
                },
                {
                  "x": 421,
                  "y": 656
                },
                {
                  "x": 419,
                  "y": 733
                },
                {
                  "x": 353,
                  "y": 733
                }
              ],
              "confidence": 0.905
            },
            {
              "text": "leads",
              "boundingPolygon": [
                {
                  "x": 435,
                  "y": 656
                },
                {
                  "x": 552,
                  "y": 658
                },
                {
                  "x": 551,
                  "y": 731
                },
                {
                  "x": 433,
                  "y": 733
                }
              ],
              "confidence": 0.917
            },
            {
              "text": "me",
              "boundingPolygon": [
                {
                  "x": 566,
                  "y": 658
                },
                {
                  "x": 654,
                  "y": 661
                },
                {
                  "x": 654,
                  "y": 730
                },
                {
                  "x": 566,
                  "y": 731
                }
              ],
              "confidence": 0.952
            },
            {
              "text": "me",
              "boundingPolygon": [
                {
                  "x": 683,
                  "y": 662
                },
                {
                  "x": 767,
                  "y": 666
                },
                {
                  "x": 768,
                  "y": 728
                },
                {
                  "x": 683,
                  "y": 729
                }
              ],
              "confidence": 0.985
            }
          ]
        },
        {
          "text": "besiade mne waers",
          "boundingPolygon": [
            {
              "x": 338,
              "y": 734
            },
            {
              "x": 804,
              "y": 738
            },
            {
              "x": 804,
              "y": 800
            },
            {
              "x": 338,
              "y": 799
            }
          ],
          "words": [
            {
              "text": "besiade",
              "boundingPolygon": [
                {
                  "x": 338,
                  "y": 735
                },
                {
                  "x": 522,
                  "y": 737
                },
                {
                  "x": 521,
                  "y": 796
                },
                {
                  "x": 338,
                  "y": 800
                }
              ],
              "confidence": 0.904
            },
            {
              "text": "mne",
              "boundingPolygon": [
                {
                  "x": 538,
                  "y": 737
                },
                {
                  "x": 642,
                  "y": 739
                },
                {
                  "x": 641,
                  "y": 796
                },
                {
                  "x": 537,
                  "y": 796
                }
              ],
              "confidence": 0.917
            },
            {
              "text": "waers",
              "boundingPolygon": [
                {
                  "x": 654,
                  "y": 740
                },
                {
                  "x": 804,
                  "y": 744
                },
                {
                  "x": 802,
                  "y": 798
                },
                {
                  "x": 653,
                  "y": 796
                }
              ],
              "confidence": 0.161
            }
          ]
        },
        {
          "text": "beiiade still vaters.",
          "boundingPolygon": [
            {
              "x": 336,
              "y": 799
            },
            {
              "x": 785,
              "y": 799
            },
            {
              "x": 785,
              "y": 869
            },
            {
              "x": 336,
              "y": 870
            }
          ],
          "words": [
            {
              "text": "beiiade",
              "boundingPolygon": [
                {
                  "x": 338,
                  "y": 804
                },
                {
                  "x": 503,
                  "y": 800
                },
                {
                  "x": 502,
                  "y": 868
                },
                {
                  "x": 337,
                  "y": 870
                }
              ],
              "confidence": 0.587
            },
            {
              "text": "still",
              "boundingPolygon": [
                {
                  "x": 516,
                  "y": 800
                },
                {
                  "x": 601,
                  "y": 799
                },
                {
                  "x": 601,
                  "y": 868
                },
                {
                  "x": 516,
                  "y": 868
                }
              ],
              "confidence": 0.993
            },
            {
              "text": "vaters.",
              "boundingPolygon": [
                {
                  "x": 615,
                  "y": 799
                },
                {
                  "x": 784,
                  "y": 802
                },
                {
                  "x": 784,
                  "y": 870
                },
                {
                  "x": 614,
                  "y": 868
                }
              ],
              "confidence": 0.958
            }
          ]
        }
      ]
    }
  ]